lt_gee_py-0.0.7.dist-info/licenses/LICENSE
ltgee/__init__.py
ltgee/gee_utils.py
ltgee/landtrendr.py
lt_gee_py-0.0.7.dist-info/METADATA
lt_gee_py-0.0.7.dist-info/WHEEL
lt_gee_py-0.0.7.dist-info/top_level.txt
lt_gee_py-0.0.7.dist-info/RECORD
