Metadata-Version: 2.4
Name: lt-gee-py
Version: 0.0.7
Summary: Python interface to the Google Earth Engine implementation of the LandTrendr spectral-temporal segmentation algorithm.
Author-email: Myscon Truong <myscontruong@gmail.com>, Robert Kennedy <robert.kennedy@oregonstate.edu>, Peter Clary <clarype@oregonstate.edu>
License:                                  Apache License
Project-URL: repository, https://github.com/eMapR/lt-gee-py
Project-URL: issue_tracker, https://github.com/eMapR/lt-gee-py/issues
Keywords: Google Earth Engine,LandTrendr,GEE,spectral-temporal segmentation,time series analysis,land cover change detection
Classifier: Development Status :: 3 - Alpha
Classifier: Intended Audience :: Science/Research
Classifier: Programming Language :: Python :: 3.10
Classifier: Programming Language :: Python :: 3.11
Classifier: Programming Language :: Python :: 3.12
Classifier: Topic :: Scientific/Engineering :: GIS
Classifier: Topic :: Scientific/Engineering :: Image Processing
Classifier: Topic :: Scientific/Engineering :: Information Analysis
Classifier: Operating System :: OS Independent
Requires-Python: >=3.10
License-File: LICENSE
Dynamic: license-file
